aiosftp/__init__.py
aiosftp/__main__.py
aiosftp/conf.py
aiosftp/ftp.py
aiosftp/scp.py
aiosftp/user.py
aiosftp/uv.py
aiosftp/version.py
aiosftp-0.4.0.dist-info/LICENSE
aiosftp-0.4.0.dist-info/METADATA
aiosftp-0.4.0.dist-info/WHEEL
aiosftp-0.4.0.dist-info/entry_points.txt
aiosftp-0.4.0.dist-info/top_level.txt
aiosftp-0.4.0.dist-info/RECORD
