Metadata-Version: 2.1
Name: aiosftp
Version: 0.4.0
Summary: FTP/SSH/sFTP Server implementation built on to of Asyncio.Facility to deploy SSH server easily inside any project.
Home-page: https://github.com/phenobarbital/aiosftp
Author: Jesus Lara
Author-email: jesuslara@phenobarbital.info
License: Apache-2
Project-URL: Source, https://github.com/phenobarbital/aiosftp
Project-URL: Funding, https://paypal.me/phenobarbital
Project-URL: Say Thanks!, https://saythanks.io/to/phenobarbital
Keywords: ftp,ftp server,sftp server,ssh server,asyncio
Classifier: Development Status :: 4 - Beta
Classifier: Intended Audience :: Developers
Classifier: Intended Audience :: System Administrators
Classifier: Topic :: Software Development :: Libraries :: Python Modules
Classifier: Topic :: Software Development :: Build Tools
Classifier: Topic :: Software Development :: Object Brokering
Classifier: Topic :: System :: Distributed Computing
Classifier: Topic :: System :: Networking
Classifier: Operating System :: OS Independent
Classifier: Environment :: Web Environment
Classifier: Programming Language :: Python :: 3.8
Classifier: Programming Language :: Python :: 3.9
Classifier: Programming Language :: Python :: 3.10
Classifier: Programming Language :: Python :: 3.11
Classifier: Programming Language :: Python :: 3.12
Classifier: Framework :: AsyncIO
Requires-Python: >=3.8.0
License-File: LICENSE
Requires-Dist: aiohttp>=3.8.5
Requires-Dist: asyncio==3.4.3
Requires-Dist: asyncdb>=2.6.0
Requires-Dist: navconfig[default]>=1.5.0
Requires-Dist: aioftp>=0.21.4
Requires-Dist: siosocks>=0.3.0
Requires-Dist: asyncssh>=2.14.2
Provides-Extra: uvloop
Requires-Dist: uvloop>=0.20.0; extra == "uvloop"
